runcrawler/__init__.py
runcrawler/cli.py
runcrawler/logclassify.py
runcrawler/scan_log.yml
runcrawler-0.0.2.dist-info/LICENCE.md
runcrawler-0.0.2.dist-info/METADATA
runcrawler-0.0.2.dist-info/WHEEL
runcrawler-0.0.2.dist-info/entry_points.txt
runcrawler-0.0.2.dist-info/top_level.txt
runcrawler-0.0.2.dist-info/RECORD
