Metadata-Version: 2.1
Name: runcrawler
Version: 0.0.2
Summary: AVBP API
Home-page: UNKNOWN
Author-email: coop@cerfacs.fr
License: UNKNOWN
Keywords: AVBP API
Platform: UNKNOWN
Classifier: Programming Language :: Python :: 3.6
Classifier: Programming Language :: Python :: 3.7
Classifier: License :: OSI Approved :: MIT License
Requires-Dist: setuptools
Requires-Dist: numpy
Requires-Dist: pyyaml
Requires-Dist: click
